[
    {
        "ext_name_fk": 10,
        "name": "checkdate",
        "ext_min": "4.0.0",
        "ext_max": "",
        "php_min": "4.0.0",
        "php_max": "",
        "parameters": "",
        "php_excludes": ""
    },
    {
        "ext_name_fk": 10,
        "name": "date",
        "ext_min": "4.0.0",
        "ext_max": "",
        "php_min": "4.0.0",
        "php_max": "",
        "parameters": "",
        "php_excludes": ""
    },
    {
        "ext_name_fk": 10,
        "name": "date_add",
        "ext_min": "5.3.0",
        "ext_max": "",
        "php_min": "5.3.0",
        "php_max": "",
        "parameters": "",
        "php_excludes": ""
    },
    {
        "ext_name_fk": 10,
        "name": "date_create",
        "ext_min": "5.2.0",
        "ext_max": "",
        "php_min": "5.2.0",
        "php_max": "",
        "parameters": "",
        "php_excludes": ""
    },
    {
        "ext_name_fk": 10,
        "name": "date_create_from_format",
        "ext_min": "5.3.0",
        "ext_max": "",
        "php_min": "5.3.0",
        "php_max": "",
        "parameters": "",
        "php_excludes": ""
    },
    {
        "ext_name_fk": 10,
        "name": "date_create_immutable",
        "ext_min": "5.5.0",
        "ext_max": "",
        "php_min": "5.5.0",
        "php_max": "",
        "parameters": "",
        "php_excludes": ""
    },
    {
        "ext_name_fk": 10,
        "name": "date_create_immutable_from_format",
        "ext_min": "5.5.0",
        "ext_max": "",
        "php_min": "5.5.0",
        "php_max": "",
        "parameters": "",
        "php_excludes": ""
    },
    {
        "ext_name_fk": 10,
        "name": "date_date_set",
        "ext_min": "5.2.0",
        "ext_max": "",
        "php_min": "5.2.0",
        "php_max": "",
        "parameters": "",
        "php_excludes": ""
    },
    {
        "ext_name_fk": 10,
        "name": "date_default_timezone_get",
        "ext_min": "5.1.0",
        "ext_max": "",
        "php_min": "5.1.0",
        "php_max": "",
        "parameters": "",
        "php_excludes": ""
    },
    {
        "ext_name_fk": 10,
        "name": "date_default_timezone_set",
        "ext_min": "5.1.0",
        "ext_max": "",
        "php_min": "5.1.0",
        "php_max": "",
        "parameters": "",
        "php_excludes": ""
    },
    {
        "ext_name_fk": 10,
        "name": "date_diff",
        "ext_min": "5.3.0",
        "ext_max": "",
        "php_min": "5.3.0",
        "php_max": "",
        "parameters": "",
        "php_excludes": ""
    },
    {
        "ext_name_fk": 10,
        "name": "date_format",
        "ext_min": "5.2.0",
        "ext_max": "",
        "php_min": "5.2.0",
        "php_max": "",
        "parameters": "",
        "php_excludes": ""
    },
    {
        "ext_name_fk": 10,
        "name": "date_get_last_errors",
        "ext_min": "5.3.0",
        "ext_max": "",
        "php_min": "5.3.0",
        "php_max": "",
        "parameters": "",
        "php_excludes": ""
    },
    {
        "ext_name_fk": 10,
        "name": "date_interval_create_from_date_string",
        "ext_min": "5.3.0",
        "ext_max": "",
        "php_min": "5.3.0",
        "php_max": "",
        "parameters": "",
        "php_excludes": ""
    },
    {
        "ext_name_fk": 10,
        "name": "date_interval_format",
        "ext_min": "5.3.0",
        "ext_max": "",
        "php_min": "5.3.0",
        "php_max": "",
        "parameters": "",
        "php_excludes": ""
    },
    {
        "ext_name_fk": 10,
        "name": "date_isodate_set",
        "ext_min": "5.2.0",
        "ext_max": "",
        "php_min": "5.2.0",
        "php_max": "",
        "parameters": "",
        "php_excludes": ""
    },
    {
        "ext_name_fk": 10,
        "name": "date_modify",
        "ext_min": "5.2.0",
        "ext_max": "",
        "php_min": "5.2.0",
        "php_max": "",
        "parameters": "",
        "php_excludes": ""
    },
    {
        "ext_name_fk": 10,
        "name": "date_offset_get",
        "ext_min": "5.2.0",
        "ext_max": "",
        "php_min": "5.2.0",
        "php_max": "",
        "parameters": "",
        "php_excludes": ""
    },
    {
        "ext_name_fk": 10,
        "name": "date_parse",
        "ext_min": "5.2.0",
        "ext_max": "",
        "php_min": "5.2.0",
        "php_max": "",
        "parameters": "",
        "php_excludes": ""
    },
    {
        "ext_name_fk": 10,
        "name": "date_parse_from_format",
        "ext_min": "5.3.0",
        "ext_max": "",
        "php_min": "5.3.0",
        "php_max": "",
        "parameters": "",
        "php_excludes": ""
    },
    {
        "ext_name_fk": 10,
        "name": "date_sub",
        "ext_min": "5.3.0",
        "ext_max": "",
        "php_min": "5.3.0",
        "php_max": "",
        "parameters": "",
        "php_excludes": ""
    },
    {
        "ext_name_fk": 10,
        "name": "date_sun_info",
        "ext_min": "5.1.2",
        "ext_max": "",
        "php_min": "5.1.2",
        "php_max": "",
        "parameters": "",
        "php_excludes": ""
    },
    {
        "ext_name_fk": 10,
        "name": "date_sunrise",
        "ext_min": "5.0.0",
        "ext_max": "",
        "php_min": "5.0.0",
        "php_max": "",
        "parameters": "",
        "php_excludes": ""
    },
    {
        "ext_name_fk": 10,
        "name": "date_sunset",
        "ext_min": "5.0.0",
        "ext_max": "",
        "php_min": "5.0.0",
        "php_max": "",
        "parameters": "",
        "php_excludes": ""
    },
    {
        "ext_name_fk": 10,
        "name": "date_time_set",
        "ext_min": "5.2.0",
        "ext_max": "",
        "php_min": "5.2.0",
        "php_max": "",
        "parameters": "",
        "php_excludes": ""
    },
    {
        "ext_name_fk": 10,
        "name": "date_timestamp_get",
        "ext_min": "5.3.0",
        "ext_max": "",
        "php_min": "5.3.0",
        "php_max": "",
        "parameters": "",
        "php_excludes": ""
    },
    {
        "ext_name_fk": 10,
        "name": "date_timestamp_set",
        "ext_min": "5.3.0",
        "ext_max": "",
        "php_min": "5.3.0",
        "php_max": "",
        "parameters": "",
        "php_excludes": ""
    },
    {
        "ext_name_fk": 10,
        "name": "date_timezone_get",
        "ext_min": "5.2.0",
        "ext_max": "",
        "php_min": "5.2.0",
        "php_max": "",
        "parameters": "",
        "php_excludes": ""
    },
    {
        "ext_name_fk": 10,
        "name": "date_timezone_set",
        "ext_min": "5.2.0",
        "ext_max": "",
        "php_min": "5.2.0",
        "php_max": "",
        "parameters": "",
        "php_excludes": ""
    },
    {
        "ext_name_fk": 10,
        "name": "getdate",
        "ext_min": "4.0.0",
        "ext_max": "",
        "php_min": "4.0.0",
        "php_max": "",
        "parameters": "",
        "php_excludes": ""
    },
    {
        "ext_name_fk": 10,
        "name": "gmdate",
        "ext_min": "4.0.0",
        "ext_max": "",
        "php_min": "4.0.0",
        "php_max": "",
        "parameters": "",
        "php_excludes": ""
    },
    {
        "ext_name_fk": 10,
        "name": "gmmktime",
        "ext_min": "4.0.0",
        "ext_max": "",
        "php_min": "4.0.0",
        "php_max": "",
        "parameters": "",
        "php_excludes": ""
    },
    {
        "ext_name_fk": 10,
        "name": "gmstrftime",
        "ext_min": "4.0.0",
        "ext_max": "",
        "php_min": "4.0.0",
        "php_max": "",
        "parameters": "",
        "php_excludes": ""
    },
    {
        "ext_name_fk": 10,
        "name": "idate",
        "ext_min": "5.0.0",
        "ext_max": "",
        "php_min": "5.0.0",
        "php_max": "",
        "parameters": "",
        "php_excludes": ""
    },
    {
        "ext_name_fk": 10,
        "name": "localtime",
        "ext_min": "4.0.0",
        "ext_max": "",
        "php_min": "4.0.0",
        "php_max": "",
        "parameters": "",
        "php_excludes": ""
    },
    {
        "ext_name_fk": 10,
        "name": "mktime",
        "ext_min": "4.0.0",
        "ext_max": "",
        "php_min": "4.0.0",
        "php_max": "",
        "parameters": "",
        "php_excludes": ""
    },
    {
        "ext_name_fk": 10,
        "name": "strftime",
        "ext_min": "4.0.0",
        "ext_max": "",
        "php_min": "4.0.0",
        "php_max": "",
        "parameters": "",
        "php_excludes": ""
    },
    {
        "ext_name_fk": 10,
        "name": "strtotime",
        "ext_min": "4.0.0",
        "ext_max": "",
        "php_min": "4.0.0",
        "php_max": "",
        "parameters": "",
        "php_excludes": ""
    },
    {
        "ext_name_fk": 10,
        "name": "time",
        "ext_min": "4.0.0",
        "ext_max": "",
        "php_min": "4.0.0",
        "php_max": "",
        "parameters": "",
        "php_excludes": ""
    },
    {
        "ext_name_fk": 10,
        "name": "timezone_abbreviations_list",
        "ext_min": "5.1.0",
        "ext_max": "",
        "php_min": "5.1.0",
        "php_max": "",
        "parameters": "",
        "php_excludes": ""
    },
    {
        "ext_name_fk": 10,
        "name": "timezone_identifiers_list",
        "ext_min": "5.1.0",
        "ext_max": "",
        "php_min": "5.1.0",
        "php_max": "",
        "parameters": "",
        "php_excludes": ""
    },
    {
        "ext_name_fk": 10,
        "name": "timezone_location_get",
        "ext_min": "5.3.0",
        "ext_max": "",
        "php_min": "5.3.0",
        "php_max": "",
        "parameters": "",
        "php_excludes": ""
    },
    {
        "ext_name_fk": 10,
        "name": "timezone_name_from_abbr",
        "ext_min": "5.1.3",
        "ext_max": "",
        "php_min": "5.1.3",
        "php_max": "",
        "parameters": "",
        "php_excludes": ""
    },
    {
        "ext_name_fk": 10,
        "name": "timezone_name_get",
        "ext_min": "5.1.0",
        "ext_max": "",
        "php_min": "5.1.0",
        "php_max": "",
        "parameters": "",
        "php_excludes": ""
    },
    {
        "ext_name_fk": 10,
        "name": "timezone_offset_get",
        "ext_min": "5.1.0",
        "ext_max": "",
        "php_min": "5.1.0",
        "php_max": "",
        "parameters": "",
        "php_excludes": ""
    },
    {
        "ext_name_fk": 10,
        "name": "timezone_open",
        "ext_min": "5.1.0",
        "ext_max": "",
        "php_min": "5.1.0",
        "php_max": "",
        "parameters": "",
        "php_excludes": ""
    },
    {
        "ext_name_fk": 10,
        "name": "timezone_transitions_get",
        "ext_min": "5.2.0",
        "ext_max": "",
        "php_min": "5.2.0",
        "php_max": "",
        "parameters": "",
        "php_excludes": ""
    },
    {
        "ext_name_fk": 10,
        "name": "timezone_version_get",
        "ext_min": "5.3.0",
        "ext_max": "",
        "php_min": "5.3.0",
        "php_max": "",
        "parameters": "",
        "php_excludes": ""
    }
]