[
    {
        "ext_name_fk": 20,
        "name": "geoip_asnum_by_name",
        "ext_min": "1.1.0",
        "ext_max": "",
        "php_min": "4.3.0",
        "php_max": "",
        "parameters": "",
        "php_excludes": ""
    },
    {
        "ext_name_fk": 20,
        "name": "geoip_continent_code_by_name",
        "ext_min": "1.0.3",
        "ext_max": "",
        "php_min": "4.3.0",
        "php_max": "",
        "parameters": "",
        "php_excludes": ""
    },
    {
        "ext_name_fk": 20,
        "name": "geoip_country_code3_by_name",
        "ext_min": "0.2.0",
        "ext_max": "",
        "php_min": "4.3.0",
        "php_max": "",
        "parameters": "",
        "php_excludes": ""
    },
    {
        "ext_name_fk": 20,
        "name": "geoip_country_code_by_name",
        "ext_min": "0.2.0",
        "ext_max": "",
        "php_min": "4.3.0",
        "php_max": "",
        "parameters": "",
        "php_excludes": ""
    },
    {
        "ext_name_fk": 20,
        "name": "geoip_country_name_by_name",
        "ext_min": "0.2.0",
        "ext_max": "",
        "php_min": "4.3.0",
        "php_max": "",
        "parameters": "",
        "php_excludes": ""
    },
    {
        "ext_name_fk": 20,
        "name": "geoip_database_info",
        "ext_min": "0.2.0",
        "ext_max": "",
        "php_min": "4.3.0",
        "php_max": "",
        "parameters": "",
        "php_excludes": ""
    },
    {
        "ext_name_fk": 20,
        "name": "geoip_db_avail",
        "ext_min": "1.0.1",
        "ext_max": "",
        "php_min": "4.3.0",
        "php_max": "",
        "parameters": "",
        "php_excludes": ""
    },
    {
        "ext_name_fk": 20,
        "name": "geoip_db_filename",
        "ext_min": "1.0.1",
        "ext_max": "",
        "php_min": "4.3.0",
        "php_max": "",
        "parameters": "",
        "php_excludes": ""
    },
    {
        "ext_name_fk": 20,
        "name": "geoip_db_get_all_info",
        "ext_min": "1.0.1",
        "ext_max": "",
        "php_min": "4.3.0",
        "php_max": "",
        "parameters": "",
        "php_excludes": ""
    },
    {
        "ext_name_fk": 20,
        "name": "geoip_domain_by_name",
        "ext_min": "1.1.0",
        "ext_max": "",
        "php_min": "4.3.0",
        "php_max": "",
        "parameters": "",
        "php_excludes": ""
    },
    {
        "ext_name_fk": 20,
        "name": "geoip_id_by_name",
        "ext_min": "0.2.0",
        "ext_max": "",
        "php_min": "4.3.0",
        "php_max": "",
        "parameters": "",
        "php_excludes": ""
    },
    {
        "ext_name_fk": 20,
        "name": "geoip_isp_by_name",
        "ext_min": "1.0.2",
        "ext_max": "",
        "php_min": "4.3.0",
        "php_max": "",
        "parameters": "",
        "php_excludes": ""
    },
    {
        "ext_name_fk": 20,
        "name": "geoip_netspeedcell_by_name",
        "ext_min": "1.1.0",
        "ext_max": "",
        "php_min": "4.3.0",
        "php_max": "",
        "parameters": "",
        "php_excludes": ""
    },
    {
        "ext_name_fk": 20,
        "name": "geoip_org_by_name",
        "ext_min": "0.2.0",
        "ext_max": "",
        "php_min": "4.3.0",
        "php_max": "",
        "parameters": "",
        "php_excludes": ""
    },
    {
        "ext_name_fk": 20,
        "name": "geoip_record_by_name",
        "ext_min": "0.2.0",
        "ext_max": "",
        "php_min": "4.3.0",
        "php_max": "",
        "parameters": "",
        "php_excludes": ""
    },
    {
        "ext_name_fk": 20,
        "name": "geoip_region_by_name",
        "ext_min": "0.2.0",
        "ext_max": "",
        "php_min": "4.3.0",
        "php_max": "",
        "parameters": "",
        "php_excludes": ""
    },
    {
        "ext_name_fk": 20,
        "name": "geoip_region_name_by_code",
        "ext_min": "1.0.5",
        "ext_max": "",
        "php_min": "4.3.0",
        "php_max": "",
        "parameters": "",
        "php_excludes": ""
    },
    {
        "ext_name_fk": 20,
        "name": "geoip_setup_custom_directory",
        "ext_min": "1.1.0",
        "ext_max": "",
        "php_min": "4.3.0",
        "php_max": "",
        "parameters": "",
        "php_excludes": ""
    },
    {
        "ext_name_fk": 20,
        "name": "geoip_time_zone_by_country_and_region",
        "ext_min": "1.0.5",
        "ext_max": "",
        "php_min": "4.3.0",
        "php_max": "",
        "parameters": "",
        "php_excludes": ""
    }
]