[
    {
        "ext_name_fk": 25,
        "rel_version": "0.5.0",
        "rel_date": "2006-11-29",
        "rel_state": "alpha",
        "ext_max": "",
        "php_min": "5.1.0",
        "php_max": ""
    },
    {
        "ext_name_fk": 25,
        "rel_version": "0.6.0",
        "rel_date": "2006-12-07",
        "rel_state": "alpha",
        "ext_max": "",
        "php_min": "5.1.0",
        "php_max": ""
    },
    {
        "ext_name_fk": 25,
        "rel_version": "0.6.1",
        "rel_date": "2006-12-13",
        "rel_state": "alpha",
        "ext_max": "",
        "php_min": "5.1.0",
        "php_max": ""
    },
    {
        "ext_name_fk": 25,
        "rel_version": "0.6.2",
        "rel_date": "2006-12-17",
        "rel_state": "alpha",
        "ext_max": "",
        "php_min": "5.1.0",
        "php_max": ""
    },
    {
        "ext_name_fk": 25,
        "rel_version": "0.6.3",
        "rel_date": "2007-01-06",
        "rel_state": "alpha",
        "ext_max": "",
        "php_min": "5.1.0",
        "php_max": ""
    },
    {
        "ext_name_fk": 25,
        "rel_version": "0.7.0",
        "rel_date": "2007-02-17",
        "rel_state": "alpha",
        "ext_max": "",
        "php_min": "5.1.0",
        "php_max": ""
    },
    {
        "ext_name_fk": 25,
        "rel_version": "0.8.0",
        "rel_date": "2007-03-20",
        "rel_state": "alpha",
        "ext_max": "",
        "php_min": "5.1.0",
        "php_max": ""
    },
    {
        "ext_name_fk": 25,
        "rel_version": "0.8.1",
        "rel_date": "2007-03-23",
        "rel_state": "alpha",
        "ext_max": "",
        "php_min": "5.1.0",
        "php_max": ""
    },
    {
        "ext_name_fk": 25,
        "rel_version": "0.9.0",
        "rel_date": "2009-03-03",
        "rel_state": "alpha",
        "ext_max": "",
        "php_min": "5.1.0",
        "php_max": ""
    }
]