[
    {
        "ext_name_fk": 36,
        "name": "EVBUFFER_EOF",
        "ext_min": "0.0.4",
        "ext_max": "",
        "php_min": "5.3.0",
        "php_max": "",
        "php_excludes": ""
    },
    {
        "ext_name_fk": 36,
        "name": "EVBUFFER_ERROR",
        "ext_min": "0.0.4",
        "ext_max": "",
        "php_min": "5.3.0",
        "php_max": "",
        "php_excludes": ""
    },
    {
        "ext_name_fk": 36,
        "name": "EVBUFFER_READ",
        "ext_min": "0.0.4",
        "ext_max": "",
        "php_min": "5.3.0",
        "php_max": "",
        "php_excludes": ""
    },
    {
        "ext_name_fk": 36,
        "name": "EVBUFFER_TIMEOUT",
        "ext_min": "0.0.4",
        "ext_max": "",
        "php_min": "5.3.0",
        "php_max": "",
        "php_excludes": ""
    },
    {
        "ext_name_fk": 36,
        "name": "EVBUFFER_WRITE",
        "ext_min": "0.0.4",
        "ext_max": "",
        "php_min": "5.3.0",
        "php_max": "",
        "php_excludes": ""
    },
    {
        "ext_name_fk": 36,
        "name": "EVLOOP_NONBLOCK",
        "ext_min": "0.0.2",
        "ext_max": "",
        "php_min": "5.3.0",
        "php_max": "",
        "php_excludes": ""
    },
    {
        "ext_name_fk": 36,
        "name": "EVLOOP_ONCE",
        "ext_min": "0.0.2",
        "ext_max": "",
        "php_min": "5.3.0",
        "php_max": "",
        "php_excludes": ""
    },
    {
        "ext_name_fk": 36,
        "name": "EV_PERSIST",
        "ext_min": "0.0.2",
        "ext_max": "",
        "php_min": "5.3.0",
        "php_max": "",
        "php_excludes": ""
    },
    {
        "ext_name_fk": 36,
        "name": "EV_READ",
        "ext_min": "0.0.2",
        "ext_max": "",
        "php_min": "5.3.0",
        "php_max": "",
        "php_excludes": ""
    },
    {
        "ext_name_fk": 36,
        "name": "EV_SIGNAL",
        "ext_min": "0.0.2",
        "ext_max": "",
        "php_min": "5.3.0",
        "php_max": "",
        "php_excludes": ""
    },
    {
        "ext_name_fk": 36,
        "name": "EV_TIMEOUT",
        "ext_min": "0.0.2",
        "ext_max": "",
        "php_min": "5.3.0",
        "php_max": "",
        "php_excludes": ""
    },
    {
        "ext_name_fk": 36,
        "name": "EV_WRITE",
        "ext_min": "0.0.2",
        "ext_max": "",
        "php_min": "5.3.0",
        "php_max": "",
        "php_excludes": ""
    }
]