[
    {
        "ext_name_fk": 63,
        "name": "recode",
        "ext_min": "4.0.0",
        "ext_max": "",
        "php_min": "4.0.0",
        "php_max": "",
        "parameters": "",
        "php_excludes": ""
    },
    {
        "ext_name_fk": 63,
        "name": "recode_file",
        "ext_min": "4.0.0",
        "ext_max": "",
        "php_min": "4.0.0",
        "php_max": "",
        "parameters": "",
        "php_excludes": ""
    },
    {
        "ext_name_fk": 63,
        "name": "recode_string",
        "ext_min": "4.0.0",
        "ext_max": "",
        "php_min": "4.0.0",
        "php_max": "",
        "parameters": "",
        "php_excludes": ""
    }
]