[
    {
        "ext_name_fk": 64,
        "name": "Reflection",
        "ext_min": "5.0.0",
        "ext_max": "",
        "php_min": "5.0.0",
        "php_max": ""
    },
    {
        "ext_name_fk": 64,
        "name": "ReflectionClass",
        "ext_min": "5.0.0",
        "ext_max": "",
        "php_min": "5.0.0",
        "php_max": ""
    },
    {
        "ext_name_fk": 64,
        "name": "ReflectionException",
        "ext_min": "5.0.0",
        "ext_max": "",
        "php_min": "5.0.0",
        "php_max": ""
    },
    {
        "ext_name_fk": 64,
        "name": "ReflectionExtension",
        "ext_min": "5.0.0",
        "ext_max": "",
        "php_min": "5.0.0",
        "php_max": ""
    },
    {
        "ext_name_fk": 64,
        "name": "ReflectionFunction",
        "ext_min": "5.0.0",
        "ext_max": "",
        "php_min": "5.0.0",
        "php_max": ""
    },
    {
        "ext_name_fk": 64,
        "name": "ReflectionFunctionAbstract",
        "ext_min": "5.0.0",
        "ext_max": "",
        "php_min": "5.0.0",
        "php_max": ""
    },
    {
        "ext_name_fk": 64,
        "name": "ReflectionMethod",
        "ext_min": "5.0.0",
        "ext_max": "",
        "php_min": "5.0.0",
        "php_max": ""
    },
    {
        "ext_name_fk": 64,
        "name": "ReflectionObject",
        "ext_min": "5.0.0",
        "ext_max": "",
        "php_min": "5.0.0",
        "php_max": ""
    },
    {
        "ext_name_fk": 64,
        "name": "ReflectionParameter",
        "ext_min": "5.0.0",
        "ext_max": "",
        "php_min": "5.0.0",
        "php_max": ""
    },
    {
        "ext_name_fk": 64,
        "name": "ReflectionProperty",
        "ext_min": "5.0.0",
        "ext_max": "",
        "php_min": "5.0.0",
        "php_max": ""
    },
    {
        "ext_name_fk": 64,
        "name": "ReflectionZendExtension",
        "ext_min": "5.4.0",
        "ext_max": "",
        "php_min": "5.4.0",
        "php_max": ""
    }
]